[
  {
    "type": "constructor",
    "inputs": [
      {
        "name": "_usdc",
        "type": "address",
        "internalType": "address"
      }
    ],
    "stateMutability": "nonpayable"
  },
  {
    "type": "function",
    "name": "authorizedStream",
    "inputs": [],
    "outputs": [
      {
        "name": "",
        "type": "address",
        "internalType": "address"
      }
    ],
    "stateMutability": "view"
  },
  {
    "type": "function",
    "name": "campaigns",
    "inputs": [
      {
        "name": "",
        "type": "bytes32",
        "internalType": "bytes32"
      }
    ],
    "outputs": [
      {
        "name": "advertiser",
        "type": "address",
        "internalType": "address"
      },
      {
        "name": "totalBudget",
        "type": "uint256",
        "internalType": "uint256"
      },
      {
        "name": "remainingBudget",
        "type": "uint256",
        "internalType": "uint256"
      },
      {
        "name": "ratePerSecond",
        "type": "uint256",
        "internalType": "uint256"
      },
      {
        "name": "duration",
        "type": "uint256",
        "internalType": "uint256"
      },
      {
        "name": "active",
        "type": "bool",
        "internalType": "bool"
      },
      {
        "name": "createdAt",
        "type": "uint256",
        "internalType": "uint256"
      }
    ],
    "stateMutability": "view"
  },
  {
    "type": "function",
    "name": "deposit",
    "inputs": [
      {
        "name": "campaignId",
        "type": "bytes32",
        "internalType": "bytes32"
      },
      {
        "name": "amount",
        "type": "uint256",
        "internalType": "uint256"
      },
      {
        "name": "ratePerSecond",
        "type": "uint256",
        "internalType": "uint256"
      },
      {
        "name": "duration",
        "type": "uint256",
        "internalType": "uint256"
      }
    ],
    "outputs": [],
    "stateMutability": "nonpayable"
  },
  {
    "type": "function",
    "name": "getCampaign",
    "inputs": [
      {
        "name": "campaignId",
        "type": "bytes32",
        "internalType": "bytes32"
      }
    ],
    "outputs": [
      {
        "name": "",
        "type": "tuple",
        "internalType": "struct VistaEscrow.Campaign",
        "components": [
          {
            "name": "advertiser",
            "type": "address",
            "internalType": "address"
          },
          {
            "name": "totalBudget",
            "type": "uint256",
            "internalType": "uint256"
          },
          {
            "name": "remainingBudget",
            "type": "uint256",
            "internalType": "uint256"
          },
          {
            "name": "ratePerSecond",
            "type": "uint256",
            "internalType": "uint256"
          },
          {
            "name": "duration",
            "type": "uint256",
            "internalType": "uint256"
          },
          {
            "name": "active",
            "type": "bool",
            "internalType": "bool"
          },
          {
            "name": "createdAt",
            "type": "uint256",
            "internalType": "uint256"
          }
        ]
      }
    ],
    "stateMutability": "view"
  },
  {
    "type": "function",
    "name": "owner",
    "inputs": [],
    "outputs": [
      {
        "name": "",
        "type": "address",
        "internalType": "address"
      }
    ],
    "stateMutability": "view"
  },
  {
    "type": "function",
    "name": "payout",
    "inputs": [
      {
        "name": "campaignId",
        "type": "bytes32",
        "internalType": "bytes32"
      },
      {
        "name": "totalAmount",
        "type": "uint256",
        "internalType": "uint256"
      },
      {
        "name": "vault",
        "type": "address",
        "internalType": "address"
      },
      {
        "name": "vaultAmount",
        "type": "uint256",
        "internalType": "uint256"
      },
      {
        "name": "vistaWallet_",
        "type": "address",
        "internalType": "address"
      },
      {
        "name": "vistaAmount",
        "type": "uint256",
        "internalType": "uint256"
      }
    ],
    "outputs": [],
    "stateMutability": "nonpayable"
  },
  {
    "type": "function",
    "name": "refundRemaining",
    "inputs": [
      {
        "name": "campaignId",
        "type": "bytes32",
        "internalType": "bytes32"
      }
    ],
    "outputs": [],
    "stateMutability": "nonpayable"
  },
  {
    "type": "function",
    "name": "renounceOwnership",
    "inputs": [],
    "outputs": [],
    "stateMutability": "nonpayable"
  },
  {
    "type": "function",
    "name": "setAuthorizedStream",
    "inputs": [
      {
        "name": "stream",
        "type": "address",
        "internalType": "address"
      }
    ],
    "outputs": [],
    "stateMutability": "nonpayable"
  },
  {
    "type": "function",
    "name": "transferOwnership",
    "inputs": [
      {
        "name": "newOwner",
        "type": "address",
        "internalType": "address"
      }
    ],
    "outputs": [],
    "stateMutability": "nonpayable"
  },
  {
    "type": "function",
    "name": "usdc",
    "inputs": [],
    "outputs": [
      {
        "name": "",
        "type": "address",
        "internalType": "contract IERC20"
      }
    ],
    "stateMutability": "view"
  },
  {
    "type": "event",
    "name": "AuthorizedStreamSet",
    "inputs": [
      {
        "name": "stream",
        "type": "address",
        "indexed": true,
        "internalType": "address"
      }
    ],
    "anonymous": false
  },
  {
    "type": "event",
    "name": "CampaignCreated",
    "inputs": [
      {
        "name": "campaignId",
        "type": "bytes32",
        "indexed": true,
        "internalType": "bytes32"
      },
      {
        "name": "advertiser",
        "type": "address",
        "indexed": true,
        "internalType": "address"
      },
      {
        "name": "amount",
        "type": "uint256",
        "indexed": false,
        "internalType": "uint256"
      },
      {
        "name": "ratePerSecond",
        "type": "uint256",
        "indexed": false,
        "internalType": "uint256"
      }
    ],
    "anonymous": false
  },
  {
    "type": "event",
    "name": "CampaignEnded",
    "inputs": [
      {
        "name": "campaignId",
        "type": "bytes32",
        "indexed": true,
        "internalType": "bytes32"
      },
      {
        "name": "refundedAmount",
        "type": "uint256",
        "indexed": false,
        "internalType": "uint256"
      }
    ],
    "anonymous": false
  },
  {
    "type": "event",
    "name": "OwnershipTransferred",
    "inputs": [
      {
        "name": "previousOwner",
        "type": "address",
        "indexed": true,
        "internalType": "address"
      },
      {
        "name": "newOwner",
        "type": "address",
        "indexed": true,
        "internalType": "address"
      }
    ],
    "anonymous": false
  },
  {
    "type": "error",
    "name": "OwnableInvalidOwner",
    "inputs": [
      {
        "name": "owner",
        "type": "address",
        "internalType": "address"
      }
    ]
  },
  {
    "type": "error",
    "name": "OwnableUnauthorizedAccount",
    "inputs": [
      {
        "name": "account",
        "type": "address",
        "internalType": "address"
      }
    ]
  },
  {
    "type": "error",
    "name": "ReentrancyGuardReentrantCall",
    "inputs": []
  },
  {
    "type": "error",
    "name": "SafeERC20FailedOperation",
    "inputs": [
      {
        "name": "token",
        "type": "address",
        "internalType": "address"
      }
    ]
  }
]
